pyproject.toml
sparkden/__init__.py
sparkden/app.py
sparkden/adk/session_service.py
sparkden/assistants/__init__.py
sparkden/assistants/context_selector.py
sparkden/assistants/helpers.py
sparkden/assistants/registry.py
sparkden/assistants/agents/chunk_summarize_agent.py
sparkden/assistants/agents/merge_summarize_agent.py
sparkden/assistants/agents/summarize_agent.py
sparkden/assistants/plugins/manage_context.py
sparkden/assistants/tools/__init__.py
sparkden/assistants/tools/search_context_tool.py
sparkden/assistants/tools/search_knowledge_tool.py
sparkden/assistants/tools/summarize_context_tool.py
sparkden/assistants/tools/user_approval_tool.py
sparkden/db/init.py
sparkden/db/schema.py
sparkden/knowledge/data_loader.py
sparkden/knowledge/registry.py
sparkden/knowledge/data_parsers/base.py
sparkden/knowledge/data_parsers/file_parser.py
sparkden/knowledge/data_splitters/base.py
sparkden/knowledge/data_splitters/default_splitter.py
sparkden/knowledge/embeddings/__init__.py
sparkden/knowledge/embeddings/base.py
sparkden/knowledge/embeddings/qwen.py
sparkden/knowledge/vector_store/__init__.py
sparkden/knowledge/vector_store/base.py
sparkden/knowledge/vector_store/qdrant.py
sparkden/litellm/logger.py
sparkden/models/assistant.py
sparkden/models/knowledge.py
sparkden/models/shared.py
sparkden/models/task.py
sparkden/models/user.py
sparkden/queued_job/__init__.py
sparkden/queued_job/data_source_job.py
sparkden/queued_job/decorator.py
sparkden/queued_job/models.py
sparkden/queued_job/search_context_job.py
sparkden/queued_job/service.py
sparkden/queued_job/summarize_context_job.py
sparkden/routes/assistants.py
sparkden/routes/files.py
sparkden/routes/knowledge.py
sparkden/routes/queued_jobs.py
sparkden/routes/tasks.py
sparkden/routes/security/auth.py
sparkden/routes/security/csrf.py
sparkden/services/base.py
sparkden/services/task.py
sparkden/services/knowledge/__init__.py
sparkden/services/knowledge/collection.py
sparkden/services/knowledge/data_source.py
sparkden-0.6.7.dist-info/METADATA
sparkden-0.6.7.dist-info/WHEEL
sparkden-0.6.7.dist-info/entry_points.txt
sparkden-0.6.7.dist-info/licenses/LICENSE
sparkden-0.6.7.dist-info/RECORD
