Metadata-Version: 2.4
Name: sparkden
Version: 0.6.7
Summary: A full-stack agent framework for enterprise customers
Author-email: LiuSiyuan <farthinker@gmail.com>
License-Expression: Apache-2.0
License-File: LICENSE
Requires-Python: >=3.12
Requires-Dist: alembic>=1.15.2
Requires-Dist: bcrypt>=4.3.0
Requires-Dist: dashscope>=1.23.9
Requires-Dist: dramatiq[redis,watch]>=1.18.0
Requires-Dist: google-adk==1.12.0
Requires-Dist: langchain-text-splitters>=0.3.8
Requires-Dist: langdetect>=1.0.9
Requires-Dist: litellm>=1.74.15
Requires-Dist: litestar[sqlalchemy]>=2.16.0
Requires-Dist: minio>=7.2.15
Requires-Dist: psycopg[binary]>=3.2.9
Requires-Dist: pymupdf4llm>=0.0.27
Requires-Dist: python-dotenv>=1.1.1
Requires-Dist: qdrant-client>=1.15.0
Requires-Dist: redis>=6.2.0
Requires-Dist: uvicorn>=0.35.0
